{
    "add_command": [],
    "architecture": "x86_64",
    "author": "RedisLabs",
    "capabilities": [
        "types",
        "replica_of",
        "failover_migrate",
        "persistence_aof",
        "persistence_rdb",
        "clustering",
        "backup_restore",
        "reshard_rebalance",
        "flash",
        "crdb",
        "eviction_expiry",
        "hash_policy"
    ],
    "capability_name": "Search and query",
    "command_line_args": "",
    "commands": [
        {
            "command_arity": -1,
            "command_name": "FT.SYNUPDATE",
            "first_key": 1,
            "flags": [
                "write",
                "module"
            ],
            "last_key": 1,
            "step": 1
        },
        {
            "command_arity": -1,
            "command_name": "FT.ALIASADD",
            "first_key": 1,
            "flags": [
                "readonly",
                "module"
            ],
            "last_key": 2,
            "step": 1
        },
        {
            "command_arity": -1,
            "command_name": "FT.DICTADD",
            "first_key": 0,
            "flags": [
                "readonly",
                "module"
            ],
            "last_key": 0,
            "step": 0
        },
        {
            "command_arity": -1,
            "command_name": "FT.MGET",
            "first_key": 1,
            "flags": [
                "readonly",
                "module"
            ],
            "last_key": -1,
            "step": 1
        },
        {
            "command_arity": -1,
            "command_name": "FT.TAGVALS",
            "first_key": 1,
            "flags": [
                "readonly",
                "module"
            ],
            "last_key": 1,
            "step": 1
        },
        {
            "command_arity": -1,
            "command_name": "FT.INFO",
            "first_key": 1,
            "flags": [
                "readonly",
                "module"
            ],
            "last_key": 1,
            "step": 1
        },
        {
            "command_arity": -1,
            "command_name": "FT.EXPLAIN",
            "first_key": 1,
            "flags": [
                "readonly",
                "module"
            ],
            "last_key": 1,
            "step": 1
        },
        {
            "command_arity": -1,
            "command_name": "FT.CONFIG",
            "first_key": 0,
            "flags": [
                "readonly",
                "module"
            ],
            "last_key": 0,
            "step": 0
        },
        {
            "command_arity": -1,
            "command_name": "FT.SUGGET",
            "first_key": 1,
            "flags": [
                "readonly",
                "module"
            ],
            "last_key": 1,
            "step": 1
        },
        {
            "command_arity": -1,
            "command_name": "FT.ALTER",
            "first_key": 1,
            "flags": [
                "write",
                "module"
            ],
            "last_key": 1,
            "step": 1
        },
        {
            "command_arity": -1,
            "command_name": "FT.DROP",
            "first_key": 1,
            "flags": [
                "write",
                "module"
            ],
            "last_key": 1,
            "step": 1
        },
        {
            "command_arity": -1,
            "command_name": "FT.SAFEADD",
            "first_key": 1,
            "flags": [
                "write",
                "denyoom",
                "module"
            ],
            "last_key": 2,
            "step": 1
        },
        {
            "command_arity": -2,
            "command_name": "FT.DEBUG",
            "first_key": 0,
            "flags": [
                "readonly",
                "module"
            ],
            "last_key": 0,
            "step": 0
        },
        {
            "command_arity": -1,
            "command_name": "FT.SUGDEL",
            "first_key": 1,
            "flags": [
                "write",
                "module"
            ],
            "last_key": 1,
            "step": 1
        },
        {
            "command_arity": -1,
            "command_name": "FT._CREATEIFNX",
            "first_key": 1,
            "flags": [
                "write",
                "denyoom",
                "module"
            ],
            "last_key": 1,
            "step": 1
        },
        {
            "command_arity": -1,
            "command_name": "FT.PROFILE",
            "first_key": 1,
            "flags": [
                "readonly",
                "module"
            ],
            "last_key": 1,
            "step": 1
        },
        {
            "command_arity": -1,
            "command_name": "FT._DROPINDEXIFX",
            "first_key": 1,
            "flags": [
                "write",
                "module"
            ],
            "last_key": 1,
            "step": 1
        },
        {
            "command_arity": -1,
            "command_name": "FT.DROPINDEX",
            "first_key": 1,
            "flags": [
                "write",
                "module"
            ],
            "last_key": 1,
            "step": 1
        },
        {
            "command_arity": -1,
            "command_name": "FT.SPELLCHECK",
            "first_key": 1,
            "flags": [
                "readonly",
                "module"
            ],
            "last_key": 1,
            "step": 1
        },
        {
            "command_arity": -1,
            "command_name": "FT._LIST",
            "first_key": 0,
            "flags": [
                "readonly",
                "module"
            ],
            "last_key": 0,
            "step": 0
        },
        {
            "command_arity": -1,
            "command_name": "FT.AGGREGATE",
            "first_key": 1,
            "flags": [
                "readonly",
                "module"
            ],
            "last_key": 1,
            "step": 1
        },
        {
            "command_arity": -1,
            "command_name": "FT.DEL",
            "first_key": 1,
            "flags": [
                "write",
                "module"
            ],
            "last_key": 2,
            "step": 1
        },
        {
            "command_arity": -1,
            "command_name": "FT._ALIASDELIFX",
            "first_key": 1,
            "flags": [
                "readonly",
                "module"
            ],
            "last_key": 1,
            "step": 1
        },
        {
            "command_arity": -1,
            "command_name": "FT.GET",
            "first_key": 1,
            "flags": [
                "readonly",
                "module"
            ],
            "last_key": 2,
            "step": 1
        },
        {
            "command_arity": -1,
            "command_name": "FT.SUGADD",
            "first_key": 1,
            "flags": [
                "write",
                "denyoom",
                "module"
            ],
            "last_key": 1,
            "step": 1
        },
        {
            "command_arity": -1,
            "command_name": "FT._ALTERIFNX",
            "first_key": 1,
            "flags": [
                "write",
                "module"
            ],
            "last_key": 1,
            "step": 1
        },
        {
            "command_arity": -1,
            "command_name": "FT._DROPIFX",
            "first_key": 1,
            "flags": [
                "write",
                "module"
            ],
            "last_key": 1,
            "step": 1
        },
        {
            "command_arity": -1,
            "command_name": "FT.SUGLEN",
            "first_key": 1,
            "flags": [
                "readonly",
                "module"
            ],
            "last_key": 1,
            "step": 1
        },
        {
            "command_arity": -1,
            "command_name": "FT.CURSOR",
            "first_key": 2,
            "flags": [
                "readonly",
                "module"
            ],
            "last_key": 2,
            "step": 1
        },
        {
            "command_arity": -1,
            "command_name": "FT._ALIASADDIFNX",
            "first_key": 1,
            "flags": [
                "readonly",
                "module"
            ],
            "last_key": 2,
            "step": 1
        },
        {
            "command_arity": -1,
            "command_name": "FT.ALIASDEL",
            "first_key": 1,
            "flags": [
                "readonly",
                "module"
            ],
            "last_key": 1,
            "step": 1
        },
        {
            "command_arity": -1,
            "command_name": "FT.DICTDUMP",
            "first_key": 0,
            "flags": [
                "readonly",
                "module"
            ],
            "last_key": 0,
            "step": 0
        },
        {
            "command_arity": -1,
            "command_name": "FT.CREATE",
            "first_key": 1,
            "flags": [
                "write",
                "denyoom",
                "module"
            ],
            "last_key": 1,
            "step": 1
        },
        {
            "command_arity": -1,
            "command_name": "FT.EXPLAINCLI",
            "first_key": 1,
            "flags": [
                "readonly",
                "module"
            ],
            "last_key": 1,
            "step": 1
        },
        {
            "command_arity": -1,
            "command_name": "FT.ADD",
            "first_key": 1,
            "flags": [
                "write",
                "denyoom",
                "module"
            ],
            "last_key": 2,
            "step": 1
        },
        {
            "command_arity": -1,
            "command_name": "FT.SYNDUMP",
            "first_key": 1,
            "flags": [
                "readonly",
                "module"
            ],
            "last_key": 1,
            "step": 1
        },
        {
            "command_arity": -1,
            "command_name": "FT.ALIASUPDATE",
            "first_key": 1,
            "flags": [
                "readonly",
                "module"
            ],
            "last_key": 2,
            "step": 1
        },
        {
            "command_arity": -1,
            "command_name": "FT.DICTDEL",
            "first_key": 0,
            "flags": [
                "readonly",
                "module"
            ],
            "last_key": 0,
            "step": 0
        },
        {
            "command_arity": -1,
            "command_name": "FT.SEARCH",
            "first_key": 1,
            "flags": [
                "readonly",
                "module"
            ],
            "last_key": 1,
            "step": 1
        },
        {
            "command_arity": -1,
            "command_name": "FT.SYNADD",
            "first_key": 1,
            "flags": [
                "write",
                "module"
            ],
            "last_key": 1,
            "step": 1
        }
    ],
    "compatible_redis_version": "8.0",
    "config_command": "FT.CONFIG SET",
    "crdb": {},
    "dependencies": {},
    "description": "High performance search index on top of redis",
    "display_name": "RediSearch 2",
    "email": "meir@redislabs.com",
    "exclude_commands": [],
    "git_sha": "b'6d25a0b1dc2f6c3c97cd7e33ba39a936c20f093e'",
    "homepage": "http://redisearch.io",
    "license": "Redis Source Available License 2.0 (RSALv2) or the Server Side Public License v1 (SSPLv1)",
    "min_redis_pack_version": "7.6",
    "min_redis_version": "7.4",
    "module_file": "redisearch.so.debug",
    "module_name": "search",
    "operating_systems": [
        "ubuntu20"
    ],
    "optional-dependencies": {},
    "os": "Linux",
    "overide_command": [],
    "ramp_format_version": 1,
    "semantic_version": "2.10.12",
    "sha256": "d3deecafd7937dc09c5ebcbc9852044787dd45f408f5624efd5398dcb8b86cf3",
    "version": 21012.0
}
